[
  {
    "key": {
      "remoteJid": "94756937488@s.whatsapp.net",
      "fromMe": false,
      "id": "3A631EBD85B65003140A"
    },
    "messageTimestamp": 1720111833,
    "pushName": "Anjali Henriyat",
    "broadcast": false,
    "message": {
      "extendedTextMessage": {
        "text": "kmk n",
        "contextInfo": {
          "stanzaId": "258324B636B42CD007AB1E55365D4219",
          "participant": "94787177718@s.whatsapp.net",
          "quotedMessage": {
            "conversation": "Bella galawela yai oka ochchara karakala 😒"
          },
          "mentionedJid": [
            "94787177718@s.whatsapp.net"
          ]
        }
      },
      "messageContextInfo": {
        "deviceListMetadata": {
          "senderTimestamp": "1720107720",
          "recipientKeyHash": "evpW2Z/kP9RDzA==",
          "recipientTimestamp": "1720100385"
        },
        "deviceListMetadataVersion": 2
      }
    },
    "id": "3A631EBD85B65003140A",
    "chat": "94756937488@s.whatsapp.net",
    "fromMe": false,
    "isGroup": false,
    "sender": "94756937488@s.whatsapp.net",
    "type": "extendedTextMessage",
    "msg": {
      "text": "kmk n",
      "contextInfo": {
        "stanzaId": "258324B636B42CD007AB1E55365D4219",
        "participant": "94787177718@s.whatsapp.net",
        "quotedMessage": {
          "conversation": "Bella galawela yai oka ochchara karakala 😒"
        },
        "mentionedJid": [
          "94787177718@s.whatsapp.net"
        ]
      }
    },
    "mentionUser": [
      "94787177718@s.whatsapp.net"
    ],
    "body": "kmk n",
    "quoted": {
      "conversation": "Bella galawela yai oka ochchara karakala 😒"
    }
  }
]